{"teams": {"t1": {"n": "Ireland", "p": [{"id": "24611", "name": "William Porterfield"}, {"id": "245287", "name": "Kenny Carroll"}, {"id": "24598", "name": "Eoin Morgan"}, {"id": "24289", "name": "Niall O'Brien"}, {"id": "24605", "name": "Kevin O'Brien"}, {"id": "6038", "name": "Trent Johnston"}, {"id": "24251", "name": "Kyle McCallan"}, {"id": "24286", "name": "Andrew White"}, {"id": "24243", "name": "Peter Gillespie"}, {"id": "243942", "name": "Dave Langford-Smith"}, {"id": "44102", "name": "Andre Botha"}], "t": "0/0", "w": []}, "t2": {"n": "Kenya", "p": [{"id": "24750", "name": "Morris Ouma"}, {"id": "24760", "name": "David Obuya"}, {"id": "238612", "name": "Nehemiah Odhiambo"}, {"id": "24728", "name": "Steve Tikolo"}, {"id": "24790", "name": "Tanmay Mishra"}, {"id": "24719", "name": "Ravi Shah"}, {"id": "24697", "name": "Jimmy Kamande"}, {"id": "24752", "name": "Collins Obuya"}, {"id": "24705", "name": "Thomas Odoyo"}, {"id": "24762", "name": "Peter Ongondo"}, {"id": "254114", "name": "Hiren Varaiya"}], "t": "0/0", "w": []}}, "runs": {"inn1": [], "inn2": []}}